Changelog.rst
Developer_Manual.rst
LICENSE.txt
MANIFEST.in
README.rst
pyproject.toml
setup.cfg
setup.py
BLooDNiNjA.egg-info/PKG-INFO
BLooDNiNjA.egg-info/SOURCES.txt
BLooDNiNjA.egg-info/dependency_links.txt
BLooDNiNjA.egg-info/entry_points.txt
BLooDNiNjA.egg-info/not-zip-safe
BLooDNiNjA.egg-info/requires.txt
BLooDNiNjA.egg-info/top_level.txt
Bloodelf/Builtins.py
Bloodelf/BytecodeCaching.py
Bloodelf/Bytecodes.py
Bloodelf/CacheCleanup.py
Bloodelf/Constants.py
Bloodelf/Errors.py
Bloodelf/HardImportRegistry.py
Bloodelf/MainControl.py
Bloodelf/ModuleRegistry.py
Bloodelf/OptionParsing.py
Bloodelf/Options.py
Bloodelf/OutputDirectories.py
Bloodelf/PostProcessing.py
Bloodelf/Progress.py
Bloodelf/PythonFlavors.py
Bloodelf/PythonOperators.py
Bloodelf/PythonVersions.py
Bloodelf/Serialization.py
Bloodelf/SourceCodeReferences.py
Bloodelf/Tracing.py
Bloodelf/TreeXML.py
Bloodelf/Variables.py
Bloodelf/Version.py
Bloodelf/__init__.py
Bloodelf/__main__.py
Bloodelf/__past__.py
Bloodelf/build/Backend.scons
Bloodelf/build/CCompilerVersion.scons
Bloodelf/build/DataComposerInterface.py
Bloodelf/build/Offsets.scons
Bloodelf/build/Onefile.scons
Bloodelf/build/SconsCaching.py
Bloodelf/build/SconsCompilerSettings.py
Bloodelf/build/SconsHacks.py
Bloodelf/build/SconsInterface.py
Bloodelf/build/SconsProgress.py
Bloodelf/build/SconsSpawn.py
Bloodelf/build/SconsUtils.py
Bloodelf/build/__init__.py
Bloodelf/build/include/SajadMr/allocator.h
Bloodelf/build/include/SajadMr/builtins.h
Bloodelf/build/include/SajadMr/calling.h
Bloodelf/build/include/SajadMr/checkers.h
Bloodelf/build/include/SajadMr/checksum_tools.h
Bloodelf/build/include/SajadMr/compiled_asyncgen.h
Bloodelf/build/include/SajadMr/compiled_cell.h
Bloodelf/build/include/SajadMr/compiled_coroutine.h
Bloodelf/build/include/SajadMr/compiled_frame.h
Bloodelf/build/include/SajadMr/compiled_function.h
Bloodelf/build/include/SajadMr/compiled_generator.h
Bloodelf/build/include/SajadMr/compiled_method.h
Bloodelf/build/include/SajadMr/constants.h
Bloodelf/build/include/SajadMr/constants_blob.h
Bloodelf/build/include/SajadMr/debug_settings.h
Bloodelf/build/include/SajadMr/environment_variables.h
Bloodelf/build/include/SajadMr/environment_variables_system.h
